<?xml version="1.0" encoding="UTF-8"?>
<Device2EM xmlns="http://www.sma.de/communication/schema/SEMP/v1">
	<DeviceInfo>
		<Identification>
			<DeviceId>F-00000001-000000000001-00</DeviceId>
			<DeviceName>SMI53M72EU</DeviceName>
			<DeviceType>DishWasher</DeviceType>
			<DeviceSerial>01234567890</DeviceSerial>
			<DeviceVendor>Bosch</DeviceVendor>
		</Identification>
		<Characteristics>
			<MaxPowerConsumption>2400</MaxPowerConsumption>
		</Characteristics>
		<Capabilities>
			<CurrentPower>
				<Method>Measurement</Method>
			</CurrentPower>
			<Interruptions>
				<InterruptionsAllowed>false</InterruptionsAllowed>
			</Interruptions>
		</Capabilities>
	</DeviceInfo>

    <DeviceStatus>
        <DeviceId>F-00000001-000000000001-00</DeviceId>
        <EMSignalsAccepted>false</EMSignalsAccepted>
        <Status>Offline</Status>
    </DeviceStatus>
	
</Device2EM>
